README.rst
setup.py
tailpy/__init__.py
tailpy/tailer.py
tailpy.egg-info/PKG-INFO
tailpy.egg-info/SOURCES.txt
tailpy.egg-info/dependency_links.txt
tailpy.egg-info/entry_points.txt
tailpy.egg-info/not-zip-safe
tailpy.egg-info/requires.txt
tailpy.egg-info/top_level.txt